datasette_upload_dbs/__init__.py
datasette_upload_dbs/templates/upload_dbs.html
datasette_upload_dbs-0.3.2.dist-info/LICENSE
datasette_upload_dbs-0.3.2.dist-info/METADATA
datasette_upload_dbs-0.3.2.dist-info/WHEEL
datasette_upload_dbs-0.3.2.dist-info/entry_points.txt
datasette_upload_dbs-0.3.2.dist-info/top_level.txt
datasette_upload_dbs-0.3.2.dist-info/RECORD
