Metadata-Version: 2.1
Name: datasette-upload-dbs
Version: 0.3.2
Summary: Upload SQLite database files to Datasette
Home-page: https://github.com/simonw/datasette-upload-dbs
Author: Simon Willison
License: Apache License, Version 2.0
Project-URL: Issues, https://github.com/simonw/datasette-upload-dbs/issues
Project-URL: CI, https://github.com/simonw/datasette-upload-dbs/actions
Project-URL: Changelog, https://github.com/simonw/datasette-upload-dbs/releases
Classifier: Framework :: Datasette
Classifier: License :: OSI Approved :: Apache Software License
Requires-Python: >=3.7
License-File: LICENSE
Requires-Dist: datasette
Requires-Dist: starlette
Provides-Extra: test
Requires-Dist: pytest ; extra == 'test'
Requires-Dist: pytest-asyncio ; extra == 'test'
